pydeptree/__init__.py
pydeptree/__main__.py
pydeptree/cli.py
pydeptree/cli_advanced.py
pydeptree/cli_enhanced.py
pydeptree/py.typed
pydeptree-0.3.21.dist-info/licenses/LICENSE
pydeptree-0.3.21.dist-info/METADATA
pydeptree-0.3.21.dist-info/WHEEL
pydeptree-0.3.21.dist-info/entry_points.txt
pydeptree-0.3.21.dist-info/top_level.txt
pydeptree-0.3.21.dist-info/RECORD
