Metadata-Version: 2.4
Name: pydeptree
Version: 0.3.21
Summary: A Python dependency tree analyzer with rich terminal output, and code quality features.
Author: Todd Faucheux
Author-email: Todd Faucheux <tfaucheux@gmail.com>
Maintainer-email: Todd Faucheux <tfaucheux@gmail.com>
License: MIT
Project-URL: Homepage, https://github.com/tfaucheux/pydeptree
Project-URL: Documentation, https://github.com/tfaucheux/pydeptree#readme
Project-URL: Repository, https://github.com/tfaucheux/pydeptree.git
Project-URL: Bug Tracker, https://github.com/tfaucheux/pydeptree/issues
Project-URL: Changelog, https://github.com/tfaucheux/pydeptree/blob/main/CHANGELOG.md
Keywords: dependency,analysis,tree,ast,development,python,import,dependency-tree,dependency-graph,module-analysis,code-analysis,static-analysis,visualization,cli,terminal,deptree,requirements
Classifier: Development Status :: 4 - Beta
Classifier: Environment :: Console
Classifier: Intended Audience :: Developers
Classifier: License :: OSI Approved :: MIT License
Classifier: Operating System :: OS Independent
Classifier: Programming Language :: Python :: 3
Classifier: Programming Language :: Python :: 3.7
Classifier: Programming Language :: Python :: 3.8
Classifier: Programming Language :: Python :: 3.9
Classifier: Programming Language :: Python :: 3.10
Classifier: Programming Language :: Python :: 3.11
Classifier: Programming Language :: Python :: 3.12
Classifier: Topic :: Software Development :: Libraries :: Python Modules
Classifier: Topic :: Software Development :: Quality Assurance
Requires-Python: >=3.7
License-File: LICENSE
Requires-Dist: click<9.0,>=8.0
Requires-Dist: rich<14.0,>=12.0
Requires-Dist: ruff>=0.1.0
Provides-Extra: dev
Requires-Dist: pytest>=7.0; extra == "dev"
Requires-Dist: pytest-cov>=4.0; extra == "dev"
Requires-Dist: black>=23.0; extra == "dev"
Requires-Dist: ruff>=0.1.0; extra == "dev"
Requires-Dist: mypy>=1.0; extra == "dev"
Requires-Dist: build>=0.10; extra == "dev"
Requires-Dist: twine>=4.0; extra == "dev"
Dynamic: author
Dynamic: license-file
Dynamic: requires-python
